NanoRepeat/__init__.py
NanoRepeat/nanoRepeat.py
NanoRepeat/nanoRepeat_bam.py
NanoRepeat/nanoRepeat_joint.py
NanoRepeat/paf.py
NanoRepeat/repeat_region.py
NanoRepeat/split_alleles.py
NanoRepeat/tk.py
nanorepeat-1.8.3.data/data/LICENSE
nanorepeat-1.8.3.data/scripts/nanoRepeat.py
nanorepeat-1.8.3.data/scripts/nanoRepeat_joint.py
nanorepeat-1.8.3.dist-info/licenses/LICENSE
nanorepeat-1.8.3.dist-info/METADATA
nanorepeat-1.8.3.dist-info/WHEEL
nanorepeat-1.8.3.dist-info/entry_points.txt
nanorepeat-1.8.3.dist-info/top_level.txt
nanorepeat-1.8.3.dist-info/RECORD
