Metadata-Version: 2.4
Name: NanoRepeat
Version: 1.8.3
Summary: NanoRepeat: quantification of Short Tandem Repeats (STRs) from long-read sequencing data
Home-page: https://github.com/WGLab/NanoRepeat
Author: Li Fang, Kai Wang
Author-email: "Li Fang, Kai Wang" <fangli9@mail.sysu.edu.cn>
License: MIT
Project-URL: Homepage, https://github.com/WGLab/NanoRepeat
Requires-Python: >=3.7
License-File: LICENSE
Requires-Dist: matplotlib>=3.4.0
Requires-Dist: numpy>=1.21.6
Requires-Dist: scikit-learn>=0.22.1
Requires-Dist: pysam>=0.17.0
Requires-Dist: pyminimap2>=2.30.0
Requires-Dist: levenshtein>=0.25
Dynamic: author
Dynamic: home-page
Dynamic: license-file
